frameml/__init__.py
frameml-0.1.4.dist-info/LICENSE
frameml-0.1.4.dist-info/METADATA
frameml-0.1.4.dist-info/WHEEL
frameml-0.1.4.dist-info/top_level.txt
frameml-0.1.4.dist-info/RECORD
