Metadata-Version: 2.1
Name: frameml
Version: 0.1.4
Summary: A lightweight markup language for interacting with machine learning models
Author: Jake Downie, Ronan Maharaj
Project-URL: homepage, https://github.com/ranger-labs/FrameML
Project-URL: repository, https://github.com/ranger-labs/FrameML
Requires-Python: >=3.6
License-File: LICENSE
